src/__init__.py
src/cli.py
src/eda_analyzer.py
src/loader.py
src/narrator.py
src/orchestrator.py
src/preprocessor.py
src/quality_scorer.py
src/report_builder.py
datasetsense-0.1.1.dist-info/METADATA
datasetsense-0.1.1.dist-info/WHEEL
datasetsense-0.1.1.dist-info/entry_points.txt
datasetsense-0.1.1.dist-info/licenses/LICENSE
datasetsense-0.1.1.dist-info/RECORD
