Metadata-Version: 2.4
Name: datasetsense
Version: 0.1.1
Summary: Automated EDA Narrator + Data Quality Scoring Tool
Project-URL: Homepage, https://github.com/Alan-Turing18this-Year/Automated-EDA-Narrator-Data-Quality-Scoring-Tool
Author: Mark Oraño, Jomar Ligas, Lex Lumantas, Philip Tupas, Josh Ganhinhin
License: MIT
License-File: LICENSE
Classifier: License :: OSI Approved :: MIT License
Classifier: Operating System :: OS Independent
Classifier: Programming Language :: Python :: 3
Classifier: Topic :: Scientific/Engineering :: Information Analysis
Requires-Python: >=3.8
Requires-Dist: numpy
Requires-Dist: pandas>=1.5
Requires-Dist: python-dateutil
Requires-Dist: scipy
Requires-Dist: tabulate
